chatgpter/__init__.py
chatgpter/__main__.py
chatgpter/app.py
chatgpter/model.py
go_chatgpt-0.0.6.dist-info/LICENSE
go_chatgpt-0.0.6.dist-info/METADATA
go_chatgpt-0.0.6.dist-info/WHEEL
go_chatgpt-0.0.6.dist-info/entry_points.txt
go_chatgpt-0.0.6.dist-info/top_level.txt
go_chatgpt-0.0.6.dist-info/RECORD
