Metadata-Version: 2.1
Name: go-chatgpt
Version: 0.0.6
Summary: Quick call to openai chatgpt api web page
Home-page: https://github.com/RedHeartSecretMan/go_chatgpt
Author: HaoDaXia
Author-email: wh18307094479@gmail.com
License: MIT
Requires-Python: >=3.8
License-File: LICENSE
Requires-Dist: gradio (==3.23.0)
Requires-Dist: matplotlib (==3.7.0)
Requires-Dist: mdtex2html (==1.2.0)
Requires-Dist: openai (==0.27.2)
Requires-Dist: requests (==2.28.2)
Requires-Dist: setuptools (==65.6.3)
Requires-Dist: tiktoken (==0.3.1)
